[{"_allAttributes":null,"_properties":null,"_methods":null,"file":"/Users/rishabh.rishabh/Documents/GitHub/LWC_Record/force-app/main/default/lwc/agen2/agen2.js","metadata":{"decorators":[],"classMembers":[],"declarationLoc":{"start":{"line":3,"column":0},"end":{"line":3,"column":54}},"doc":"","exports":[{"type":"ExportDefaultDeclaration"}]},"updatedAt":"2025-04-01T09:59:01.026Z"},{"_allAttributes":null,"_properties":null,"_methods":null,"file":"/Users/rishabh.rishabh/Documents/GitHub/LWC_Record/force-app/main/default/lwc/agent/agent.js","metadata":{"decorators":[],"classMembers":[],"declarationLoc":{"start":{"line":2,"column":0},"end":{"line":2,"column":61}},"doc":"","exports":[{"type":"ExportDefaultDeclaration"}]},"updatedAt":"2025-04-01T09:59:01.028Z"}]